{
  "alle Spielelemente / Top-Scorer": {
    "headers": [
      "Rang",
      "",
      "Name",
      "Sätze",
      "Spiele",
      "Position",
      "Mannschaft",
      "Nation",
      "Wert1",
      "Wert2",
      "Wert3",
      "Kennzahl",
      "Wertung"
    ],
    "rows": [
      [
        "4.",
        "",
        "Dordevic, Jovana",
        "7",
        "4",
        "Außenangriff",
        "Wiesbaden",
        "Deutschland (GER)",
        "13",
        "3",
        "1",
        "46,2%",
        "15,4%"
      ],
      [
        "17.",
        "",
        "Boom, Dagmar",
        "36",
        "10",
        "Außenangriff",
        "Wiesbaden",
        "Niederlande (NED)",
        "133",
        "15",
        "10",
        "30,8%",
        "1,5%"
      ],
      [
        "24.",
        "",
        "van der Pijl, Pleun",
        "30",
        "8",
        "Außenangriff",
        "Wiesbaden",
        "Niederlande (NED)",
        "60",
        "4",
        "18",
        "25,0%",
        "-3,3%"
      ],
      [
        "59.",
        "",
        "Fernandez Gayoso, Jimena",
        "36",
        "10",
        "Diagonal",
        "Wiesbaden",
        "Spanien (ESP)",
        "98",
        "13",
        "15",
        "27,6%",
        "-13,3%"
      ],
      [
        "63.",
        "",
        "Rieger, Marlene Katharina",
        "20",
        "8",
        "Mittelblock",
        "Wiesbaden",
        "Deutschland (GER)",
        "44",
        "1",
        "6",
        "27,3%",
        "-13,6%"
      ],
      [
        "11.",
        "",
        "Bernhard, Lena",
        "10",
        "8",
        "Außenangriff",
        "Borken",
        "Deutschland (GER)",
        "24",
        "1",
        "2",
        "29,2%",
        "8,3%"
      ],
      [
        "13.",
        "",
        "Gesquiere, Amber",
        "10",
        "8",
        "Mittelblock",
        "Borken",
        "Belgien (BEL)",
        "27",
        "4",
        "3",
        "25,9%",
        "7,4%"
      ],
      [
        "16.",
        "",
        "Loker, Marika",
        "31",
        "10",
        "Diagonal",
        "Borken",
        "Deutschland (GER)",
        "90",
        "5",
        "6",
        "30,0%",
        "2,2%"
      ],
      [
        "18.",
        "",
        "Konjer, Chaine",
        "24",
        "9",
        "Zuspiel",
        "Borken",
        "Deutschland (GER)",
        "40",
        "4",
        "5",
        "27,5%",
        "0,0%"
      ],
      [
        "36.",
        "",
        "Rudde, Hannah",
        "27",
        "10",
        "Zuspiel",
        "Borken",
        "Deutschland (GER)",
        "60",
        "8",
        "5",
        "35,0%",
        "-6,7%"
      ]
    ]
  },
  "Aufschlag / Quote Aufschläge mit Wirkung": {
    "headers": [
      "Rang",
      "",
      "Name",
      "Sätze",
      "Spiele",
      "Position",
      "Mannschaft",
      "Nation",
      "Wert1",
      "Wert2",
      "Wert3",
      "Kennzahl",
      "Wertung"
    ],
    "rows": [
      [
        "3.",
        "",
        "Dordevic, Jovana",
        "7",
        "4",
        "Außenangriff",
        "Wiesbaden",
        "Deutschland (GER)",
        "13",
        "3",
        "1",
        "46,2%",
        "46,2%"
      ],
      [
        "20.",
        "",
        "Boom, Dagmar",
        "36",
        "10",
        "Außenangriff",
        "Wiesbaden",
        "Niederlande (NED)",
        "133",
        "15",
        "10",
        "30,8%",
        "30,8%"
      ],
      [
        "40.",
        "",
        "Fernandez Gayoso, Jimena",
        "36",
        "10",
        "Diagonal",
        "Wiesbaden",
        "Spanien (ESP)",
        "98",
        "13",
        "15",
        "27,6%",
        "27,6%"
      ],
      [
        "43.",
        "",
        "Rieger, Marlene Katharina",
        "20",
        "8",
        "Mittelblock",
        "Wiesbaden",
        "Deutschland (GER)",
        "44",
        "1",
        "6",
        "27,3%",
        "27,3%"
      ],
      [
        "58.",
        "",
        "Konijnenberg, Sanne",
        "37",
        "10",
        "Zuspiel",
        "Wiesbaden",
        "Niederlande (NED)",
        "148",
        "9",
        "8",
        "25,0%",
        "25,0%"
      ],
      [
        "12.",
        "",
        "Rudde, Hannah",
        "27",
        "10",
        "Zuspiel",
        "Borken",
        "Deutschland (GER)",
        "60",
        "8",
        "5",
        "35,0%",
        "35,0%"
      ],
      [
        "22.",
        "",
        "Loker, Marika",
        "31",
        "10",
        "Diagonal",
        "Borken",
        "Deutschland (GER)",
        "90",
        "5",
        "6",
        "30,0%",
        "30,0%"
      ],
      [
        "27.",
        "",
        "Bernhard, Lena",
        "10",
        "8",
        "Außenangriff",
        "Borken",
        "Deutschland (GER)",
        "24",
        "1",
        "2",
        "29,2%",
        "29,2%"
      ],
      [
        "36.",
        "",
        "Mohr, Pia",
        "27",
        "10",
        "Außenangriff",
        "Borken",
        "Deutschland (GER)",
        "64",
        "7",
        "9",
        "28,1%",
        "28,1%"
      ],
      [
        "41.",
        "",
        "Konjer, Chaine",
        "24",
        "9",
        "Zuspiel",
        "Borken",
        "Deutschland (GER)",
        "40",
        "4",
        "5",
        "27,5%",
        "27,5%"
      ]
    ]
  },
  "Annahme / Quote perfekte oder gute Annahme": {
    "headers": [
      "Rang",
      "",
      "Name",
      "Sätze",
      "Spiele",
      "Position",
      "Mannschaft",
      "Nation",
      "Wert1",
      "Wert2",
      "Wert3",
      "Kennzahl",
      "Wertung"
    ],
    "rows": [
      [
        "7.",
        "",
        "Sain, Rene",
        "37",
        "10",
        "Libero",
        "Wiesbaden",
        "Kroatien (CRO)",
        "0",
        "0",
        "0",
        "0,0%",
        "45,2%"
      ],
      [
        "13.",
        "",
        "Boom, Dagmar",
        "36",
        "10",
        "Außenangriff",
        "Wiesbaden",
        "Niederlande (NED)",
        "133",
        "15",
        "10",
        "30,8%",
        "42,6%"
      ],
      [
        "18.",
        "",
        "López Rey, Cayetana",
        "34",
        "10",
        "Außenangriff",
        "Wiesbaden",
        "Spanien (ESP)",
        "84",
        "1",
        "10",
        "23,8%",
        "38,2%"
      ],
      [
        "20.",
        "",
        "van der Pijl, Pleun",
        "30",
        "8",
        "Außenangriff",
        "Wiesbaden",
        "Niederlande (NED)",
        "60",
        "4",
        "18",
        "25,0%",
        "37,6%"
      ],
      [
        "–",
        "",
        "–",
        "–",
        "–",
        "–",
        "Wiesbaden",
        "–",
        "–",
        "–",
        "–",
        "–",
        "–"
      ],
      [
        "21.",
        "",
        "Coenders, Fabienne",
        "30",
        "10",
        "Außenangriff",
        "Borken",
        "Niederlande (NED)",
        "107",
        "8",
        "2",
        "24,3%",
        "37,2%"
      ],
      [
        "22.",
        "",
        "Hansen, Ditte Kjær",
        "28",
        "9",
        "Libero",
        "Borken",
        "Dänemark (DEN)",
        "0",
        "0",
        "0",
        "0,0%",
        "37,2%"
      ],
      [
        "26.",
        "",
        "Demirer, Melisa Nafia",
        "10",
        "6",
        "Libero",
        "Borken",
        "Deutschland (GER)",
        "0",
        "0",
        "0",
        "0,0%",
        "35,2%"
      ],
      [
        "30.",
        "",
        "Mohr, Pia",
        "27",
        "10",
        "Außenangriff",
        "Borken",
        "Deutschland (GER)",
        "64",
        "7",
        "9",
        "28,1%",
        "33,6%"
      ],
      [
        "43.",
        "",
        "Piest, Madleen",
        "19",
        "9",
        "Außenangriff",
        "Borken",
        "Deutschland (GER)",
        "29",
        "1",
        "1",
        "24,1%",
        "26,7%"
      ]
    ]
  },
  "Aufschlag / Quote Aufschlagpunkte": {
    "headers": [
      "Rang",
      "",
      "Name",
      "Sätze",
      "Spiele",
      "Position",
      "Mannschaft",
      "Nation",
      "Wert1",
      "Wert2",
      "Wert3",
      "Kennzahl",
      "Wertung"
    ],
    "rows": [
      [
        "1.",
        "",
        "Dordevic, Jovana",
        "7",
        "4",
        "Außenangriff",
        "Wiesbaden",
        "Deutschland (GER)",
        "13",
        "3",
        "1",
        "46,2%",
        "23,1%"
      ],
      [
        "13.",
        "",
        "Fernandez Gayoso, Jimena",
        "36",
        "10",
        "Diagonal",
        "Wiesbaden",
        "Spanien (ESP)",
        "98",
        "13",
        "15",
        "27,6%",
        "13,3%"
      ],
      [
        "21.",
        "",
        "Boom, Dagmar",
        "36",
        "10",
        "Außenangriff",
        "Wiesbaden",
        "Niederlande (NED)",
        "133",
        "15",
        "10",
        "30,8%",
        "11,3%"
      ],
      [
        "27.",
        "",
        "Weinmann, Hanna",
        "14",
        "9",
        "Zuspiel",
        "Wiesbaden",
        "Deutschland (GER)",
        "10",
        "1",
        "1",
        "10,0%",
        "10,0%"
      ],
      [
        "58.",
        "",
        "van der Pijl, Pleun",
        "30",
        "8",
        "Außenangriff",
        "Wiesbaden",
        "Niederlande (NED)",
        "60",
        "4",
        "18",
        "25,0%",
        "6,7%"
      ],
      [
        "10.",
        "",
        "Gesquiere, Amber",
        "10",
        "8",
        "Mittelblock",
        "Borken",
        "Belgien (BEL)",
        "27",
        "4",
        "3",
        "25,9%",
        "14,8%"
      ],
      [
        "12.",
        "",
        "Rudde, Hannah",
        "27",
        "10",
        "Zuspiel",
        "Borken",
        "Deutschland (GER)",
        "60",
        "8",
        "5",
        "35,0%",
        "13,3%"
      ],
      [
        "22.",
        "",
        "Mohr, Pia",
        "27",
        "10",
        "Außenangriff",
        "Borken",
        "Deutschland (GER)",
        "64",
        "7",
        "9",
        "28,1%",
        "10,9%"
      ],
      [
        "27.",
        "",
        "Konjer, Chaine",
        "24",
        "9",
        "Zuspiel",
        "Borken",
        "Deutschland (GER)",
        "40",
        "4",
        "5",
        "27,5%",
        "10,0%"
      ],
      [
        "41.",
        "",
        "Hövels, Sandra",
        "11",
        "9",
        "Mittelblock",
        "Borken",
        "Deutschland (GER)",
        "23",
        "2",
        "3",
        "21,7%",
        "8,7%"
      ]
    ]
  },
  "Annahme / Annahmeeffizienz": {
    "headers": [
      "Rang",
      "",
      "Name",
      "Sätze",
      "Spiele",
      "Position",
      "Mannschaft",
      "Nation",
      "Wert1",
      "Wert2",
      "Wert3",
      "Kennzahl",
      "Wertung"
    ],
    "rows": [
      [
        "8.",
        "",
        "Sain, Rene",
        "37",
        "10",
        "Libero",
        "Wiesbaden",
        "Kroatien (CRO)",
        "0",
        "0",
        "0",
        "0,0%",
        "33,9%"
      ],
      [
        "13.",
        "",
        "Boom, Dagmar",
        "36",
        "10",
        "Außenangriff",
        "Wiesbaden",
        "Niederlande (NED)",
        "133",
        "15",
        "10",
        "30,8%",
        "29,5%"
      ],
      [
        "20.",
        "",
        "López Rey, Cayetana",
        "34",
        "10",
        "Außenangriff",
        "Wiesbaden",
        "Spanien (ESP)",
        "84",
        "1",
        "10",
        "23,8%",
        "23,5%"
      ],
      [
        "34.",
        "",
        "van der Pijl, Pleun",
        "30",
        "8",
        "Außenangriff",
        "Wiesbaden",
        "Niederlande (NED)",
        "60",
        "4",
        "18",
        "25,0%",
        "14,5%"
      ],
      [
        "–",
        "",
        "–",
        "–",
        "–",
        "–",
        "Wiesbaden",
        "–",
        "–",
        "–",
        "–",
        "–",
        "–"
      ],
      [
        "24.",
        "",
        "Hansen, Ditte Kjær",
        "28",
        "9",
        "Libero",
        "Borken",
        "Dänemark (DEN)",
        "0",
        "0",
        "0",
        "0,0%",
        "20,8%"
      ],
      [
        "25.",
        "",
        "Coenders, Fabienne",
        "30",
        "10",
        "Außenangriff",
        "Borken",
        "Niederlande (NED)",
        "107",
        "8",
        "2",
        "24,3%",
        "20,5%"
      ],
      [
        "29.",
        "",
        "Mohr, Pia",
        "27",
        "10",
        "Außenangriff",
        "Borken",
        "Deutschland (GER)",
        "64",
        "7",
        "9",
        "28,1%",
        "17,6%"
      ],
      [
        "32.",
        "",
        "Demirer, Melisa Nafia",
        "10",
        "6",
        "Libero",
        "Borken",
        "Deutschland (GER)",
        "0",
        "0",
        "0",
        "0,0%",
        "14,8%"
      ],
      [
        "39.",
        "",
        "Piest, Madleen",
        "19",
        "9",
        "Außenangriff",
        "Borken",
        "Deutschland (GER)",
        "29",
        "1",
        "1",
        "24,1%",
        "10,5%"
      ]
    ]
  },
  "Angriff / Angriffseffizienz": {
    "headers": [
      "Rang",
      "",
      "Name",
      "Sätze",
      "Spiele",
      "Position",
      "Mannschaft",
      "Nation",
      "Wert1",
      "Wert2",
      "Wert3",
      "Kennzahl",
      "Wertung"
    ],
    "rows": [
      [
        "14.",
        "",
        "Clayton, Hannah",
        "32",
        "10",
        "Mittelblock",
        "Wiesbaden",
        "Vereinigte Staaten von Amerika (USA)",
        "70",
        "2",
        "14",
        "14,3%",
        "33,3%"
      ],
      [
        "15.",
        "",
        "Konijnenberg, Sanne",
        "37",
        "10",
        "Zuspiel",
        "Wiesbaden",
        "Niederlande (NED)",
        "148",
        "9",
        "8",
        "25,0%",
        "32,6%"
      ],
      [
        "24.",
        "",
        "Broekstra, Laura",
        "36",
        "10",
        "Mittelblock",
        "Wiesbaden",
        "Deutschland (GER)",
        "96",
        "4",
        "18",
        "22,9%",
        "28,6%"
      ],
      [
        "30.",
        "",
        "van der Pijl, Pleun",
        "30",
        "8",
        "Außenangriff",
        "Wiesbaden",
        "Niederlande (NED)",
        "60",
        "4",
        "18",
        "25,0%",
        "26,9%"
      ],
      [
        "42.",
        "",
        "Fernandez Gayoso, Jimena",
        "36",
        "10",
        "Diagonal",
        "Wiesbaden",
        "Spanien (ESP)",
        "98",
        "13",
        "15",
        "27,6%",
        "24,1%"
      ],
      [
        "31.",
        "",
        "Kretschmer, Lara",
        "31",
        "10",
        "Mittelblock",
        "Borken",
        "Deutschland (GER)",
        "64",
        "4",
        "16",
        "20,3%",
        "26,9%"
      ],
      [
        "38.",
        "",
        "Loker, Marika",
        "31",
        "10",
        "Diagonal",
        "Borken",
        "Deutschland (GER)",
        "90",
        "5",
        "6",
        "30,0%",
        "24,7%"
      ],
      [
        "57.",
        "",
        "Piest, Madleen",
        "19",
        "9",
        "Außenangriff",
        "Borken",
        "Deutschland (GER)",
        "29",
        "1",
        "1",
        "24,1%",
        "16,7%"
      ],
      [
        "63.",
        "",
        "Coenders, Fabienne",
        "30",
        "10",
        "Außenangriff",
        "Borken",
        "Niederlande (NED)",
        "107",
        "8",
        "2",
        "24,3%",
        "14,4%"
      ],
      [
        "67.",
        "",
        "Mohr, Pia",
        "27",
        "10",
        "Außenangriff",
        "Borken",
        "Deutschland (GER)",
        "64",
        "7",
        "9",
        "28,1%",
        "13,8%"
      ]
    ]
  },
  "Block / Blockpunkte": {
    "headers": [
      "Rang",
      "",
      "Name",
      "Sätze",
      "Spiele",
      "Position",
      "Mannschaft",
      "Nation",
      "Wert1",
      "Wert2",
      "Wert3",
      "Kennzahl",
      "Wertung"
    ],
    "rows": [
      [
        "9.",
        "",
        "Broekstra, Laura",
        "36",
        "10",
        "Mittelblock",
        "Wiesbaden",
        "Deutschland (GER)",
        "96",
        "4",
        "18",
        "22,9%",
        "21"
      ],
      [
        "17.",
        "",
        "van der Pijl, Pleun",
        "30",
        "8",
        "Außenangriff",
        "Wiesbaden",
        "Niederlande (NED)",
        "60",
        "4",
        "18",
        "25,0%",
        "14"
      ],
      [
        "25.",
        "",
        "Clayton, Hannah",
        "32",
        "10",
        "Mittelblock",
        "Wiesbaden",
        "Vereinigte Staaten von Amerika (USA)",
        "70",
        "2",
        "14",
        "14,3%",
        "12"
      ],
      [
        "34.",
        "",
        "Konijnenberg, Sanne",
        "37",
        "10",
        "Zuspiel",
        "Wiesbaden",
        "Niederlande (NED)",
        "148",
        "9",
        "8",
        "25,0%",
        "10"
      ],
      [
        "43.",
        "",
        "Fernandez Gayoso, Jimena",
        "36",
        "10",
        "Diagonal",
        "Wiesbaden",
        "Spanien (ESP)",
        "98",
        "13",
        "15",
        "27,6%",
        "8"
      ],
      [
        "10.",
        "",
        "Kretschmer, Lara",
        "31",
        "10",
        "Mittelblock",
        "Borken",
        "Deutschland (GER)",
        "64",
        "4",
        "16",
        "20,3%",
        "20"
      ],
      [
        "15.",
        "",
        "Luther, Doreen",
        "25",
        "8",
        "Mittelblock",
        "Borken",
        "Deutschland (GER)",
        "72",
        "6",
        "7",
        "23,6%",
        "15"
      ],
      [
        "43.",
        "",
        "Coenders, Fabienne",
        "30",
        "10",
        "Außenangriff",
        "Borken",
        "Niederlande (NED)",
        "107",
        "8",
        "2",
        "24,3%",
        "8"
      ],
      [
        "48.",
        "",
        "Mohr, Pia",
        "27",
        "10",
        "Außenangriff",
        "Borken",
        "Deutschland (GER)",
        "64",
        "7",
        "9",
        "28,1%",
        "7"
      ],
      [
        "61.",
        "",
        "Kastrup, Liza",
        "26",
        "10",
        "Diagonal",
        "Borken",
        "Deutschland (GER)",
        "41",
        "3",
        "6",
        "24,4%",
        "5"
      ]
    ]
  },
  "Aufschlag / Aufschlagpunkte": {
    "headers": [
      "Rang",
      "",
      "Name",
      "Sätze",
      "Spiele",
      "Position",
      "Mannschaft",
      "Nation",
      "Wert1",
      "Wert2",
      "Wert3",
      "Kennzahl",
      "Wertung"
    ],
    "rows": [
      [
        "5.",
        "",
        "Boom, Dagmar",
        "36",
        "10",
        "Außenangriff",
        "Wiesbaden",
        "Niederlande (NED)",
        "133",
        "15",
        "10",
        "30,8%",
        "15"
      ],
      [
        "9.",
        "",
        "Fernandez Gayoso, Jimena",
        "36",
        "10",
        "Diagonal",
        "Wiesbaden",
        "Spanien (ESP)",
        "98",
        "13",
        "15",
        "27,6%",
        "13"
      ],
      [
        "18.",
        "",
        "Konijnenberg, Sanne",
        "37",
        "10",
        "Zuspiel",
        "Wiesbaden",
        "Niederlande (NED)",
        "148",
        "9",
        "8",
        "25,0%",
        "9"
      ],
      [
        "56.",
        "",
        "Broekstra, Laura",
        "36",
        "10",
        "Mittelblock",
        "Wiesbaden",
        "Deutschland (GER)",
        "96",
        "4",
        "18",
        "22,9%",
        "4"
      ],
      [
        "56.",
        "",
        "van der Pijl, Pleun",
        "30",
        "8",
        "Außenangriff",
        "Wiesbaden",
        "Niederlande (NED)",
        "60",
        "4",
        "18",
        "25,0%",
        "4"
      ],
      [
        "25.",
        "",
        "Coenders, Fabienne",
        "30",
        "10",
        "Außenangriff",
        "Borken",
        "Niederlande (NED)",
        "107",
        "8",
        "2",
        "24,3%",
        "8"
      ],
      [
        "25.",
        "",
        "Rudde, Hannah",
        "27",
        "10",
        "Zuspiel",
        "Borken",
        "Deutschland (GER)",
        "60",
        "8",
        "5",
        "35,0%",
        "8"
      ],
      [
        "32.",
        "",
        "Mohr, Pia",
        "27",
        "10",
        "Außenangriff",
        "Borken",
        "Deutschland (GER)",
        "64",
        "7",
        "9",
        "28,1%",
        "7"
      ],
      [
        "40.",
        "",
        "Luther, Doreen",
        "25",
        "8",
        "Mittelblock",
        "Borken",
        "Deutschland (GER)",
        "72",
        "6",
        "7",
        "23,6%",
        "6"
      ],
      [
        "51.",
        "",
        "Loker, Marika",
        "31",
        "10",
        "Diagonal",
        "Borken",
        "Deutschland (GER)",
        "90",
        "5",
        "6",
        "30,0%",
        "5"
      ]
    ]
  },
  "Angriff / Quote Angriffspunkte": {
    "headers": [
      "Rang",
      "",
      "Name",
      "Sätze",
      "Spiele",
      "Position",
      "Mannschaft",
      "Nation",
      "Wert1",
      "Wert2",
      "Wert3",
      "Kennzahl",
      "Wertung"
    ],
    "rows": [
      [
        "21.",
        "",
        "Clayton, Hannah",
        "32",
        "10",
        "Mittelblock",
        "Wiesbaden",
        "Vereinigte Staaten von Amerika (USA)",
        "70",
        "2",
        "14",
        "14,3%",
        "44,9%"
      ],
      [
        "30.",
        "",
        "van der Pijl, Pleun",
        "30",
        "8",
        "Außenangriff",
        "Wiesbaden",
        "Niederlande (NED)",
        "60",
        "4",
        "18",
        "25,0%",
        "42,1%"
      ],
      [
        "33.",
        "",
        "Fernandez Gayoso, Jimena",
        "36",
        "10",
        "Diagonal",
        "Wiesbaden",
        "Spanien (ESP)",
        "98",
        "13",
        "15",
        "27,6%",
        "41,5%"
      ],
      [
        "34.",
        "",
        "Konijnenberg, Sanne",
        "37",
        "10",
        "Zuspiel",
        "Wiesbaden",
        "Niederlande (NED)",
        "148",
        "9",
        "8",
        "25,0%",
        "41,3%"
      ],
      [
        "35.",
        "",
        "Broekstra, Laura",
        "36",
        "10",
        "Mittelblock",
        "Wiesbaden",
        "Deutschland (GER)",
        "96",
        "4",
        "18",
        "22,9%",
        "41,0%"
      ],
      [
        "24.",
        "",
        "Kretschmer, Lara",
        "31",
        "10",
        "Mittelblock",
        "Borken",
        "Deutschland (GER)",
        "64",
        "4",
        "16",
        "20,3%",
        "43,7%"
      ],
      [
        "45.",
        "",
        "Loker, Marika",
        "31",
        "10",
        "Diagonal",
        "Borken",
        "Deutschland (GER)",
        "90",
        "5",
        "6",
        "30,0%",
        "38,7%"
      ],
      [
        "48.",
        "",
        "Piest, Madleen",
        "19",
        "9",
        "Außenangriff",
        "Borken",
        "Deutschland (GER)",
        "29",
        "1",
        "1",
        "24,1%",
        "36,7%"
      ],
      [
        "68.",
        "",
        "Luther, Doreen",
        "25",
        "8",
        "Mittelblock",
        "Borken",
        "Deutschland (GER)",
        "72",
        "6",
        "7",
        "23,6%",
        "29,6%"
      ],
      [
        "69.",
        "",
        "Mohr, Pia",
        "27",
        "10",
        "Außenangriff",
        "Borken",
        "Deutschland (GER)",
        "64",
        "7",
        "9",
        "28,1%",
        "29,6%"
      ]
    ]
  },
  "Angriff / Angriffspunkte": {
    "headers": [
      "Rang",
      "",
      "Name",
      "Sätze",
      "Spiele",
      "Position",
      "Mannschaft",
      "Nation",
      "Wert1",
      "Wert2",
      "Wert3",
      "Kennzahl",
      "Wertung"
    ],
    "rows": [
      [
        "5.",
        "",
        "Fernandez Gayoso, Jimena",
        "36",
        "10",
        "Diagonal",
        "Wiesbaden",
        "Spanien (ESP)",
        "98",
        "13",
        "15",
        "27,6%",
        "117"
      ],
      [
        "20.",
        "",
        "van der Pijl, Pleun",
        "30",
        "8",
        "Außenangriff",
        "Wiesbaden",
        "Niederlande (NED)",
        "60",
        "4",
        "18",
        "25,0%",
        "72"
      ],
      [
        "23.",
        "",
        "López Rey, Cayetana",
        "34",
        "10",
        "Außenangriff",
        "Wiesbaden",
        "Spanien (ESP)",
        "84",
        "1",
        "10",
        "23,8%",
        "71"
      ],
      [
        "30.",
        "",
        "Boom, Dagmar",
        "36",
        "10",
        "Außenangriff",
        "Wiesbaden",
        "Niederlande (NED)",
        "133",
        "15",
        "10",
        "30,8%",
        "54"
      ],
      [
        "43.",
        "",
        "Broekstra, Laura",
        "36",
        "10",
        "Mittelblock",
        "Wiesbaden",
        "Deutschland (GER)",
        "96",
        "4",
        "18",
        "22,9%",
        "43"
      ],
      [
        "20.",
        "",
        "Loker, Marika",
        "31",
        "10",
        "Diagonal",
        "Borken",
        "Deutschland (GER)",
        "90",
        "5",
        "6",
        "30,0%",
        "72"
      ],
      [
        "32.",
        "",
        "Kretschmer, Lara",
        "31",
        "10",
        "Mittelblock",
        "Borken",
        "Deutschland (GER)",
        "64",
        "4",
        "16",
        "20,3%",
        "52"
      ],
      [
        "35.",
        "",
        "Coenders, Fabienne",
        "30",
        "10",
        "Außenangriff",
        "Borken",
        "Niederlande (NED)",
        "107",
        "8",
        "2",
        "24,3%",
        "49"
      ],
      [
        "39.",
        "",
        "Mohr, Pia",
        "27",
        "10",
        "Außenangriff",
        "Borken",
        "Deutschland (GER)",
        "64",
        "7",
        "9",
        "28,1%",
        "45"
      ],
      [
        "65.",
        "",
        "Kastrup, Liza",
        "26",
        "10",
        "Diagonal",
        "Borken",
        "Deutschland (GER)",
        "41",
        "3",
        "6",
        "24,4%",
        "25"
      ]
    ]
  },
  "Aufschlag / Aufschlageffizienz": {
    "headers": [
      "Rang",
      "",
      "Name",
      "Sätze",
      "Spiele",
      "Position",
      "Mannschaft",
      "Nation",
      "Wert1",
      "Wert2",
      "Wert3",
      "Kennzahl",
      "Wertung"
    ],
    "rows": [
      [
        "4.",
        "",
        "Dordevic, Jovana",
        "7",
        "4",
        "Außenangriff",
        "Wiesbaden",
        "Deutschland (GER)",
        "13",
        "3",
        "1",
        "46,2%",
        "15,4%"
      ],
      [
        "17.",
        "",
        "Boom, Dagmar",
        "36",
        "10",
        "Außenangriff",
        "Wiesbaden",
        "Niederlande (NED)",
        "133",
        "15",
        "10",
        "30,8%",
        "1,5%"
      ],
      [
        "24.",
        "",
        "van der Pijl, Pleun",
        "30",
        "8",
        "Außenangriff",
        "Wiesbaden",
        "Niederlande (NED)",
        "60",
        "4",
        "18",
        "25,0%",
        "-3,3%"
      ],
      [
        "59.",
        "",
        "Fernandez Gayoso, Jimena",
        "36",
        "10",
        "Diagonal",
        "Wiesbaden",
        "Spanien (ESP)",
        "98",
        "13",
        "15",
        "27,6%",
        "-13,3%"
      ],
      [
        "63.",
        "",
        "Rieger, Marlene Katharina",
        "20",
        "8",
        "Mittelblock",
        "Wiesbaden",
        "Deutschland (GER)",
        "44",
        "1",
        "6",
        "27,3%",
        "-13,6%"
      ],
      [
        "11.",
        "",
        "Bernhard, Lena",
        "10",
        "8",
        "Außenangriff",
        "Borken",
        "Deutschland (GER)",
        "24",
        "1",
        "2",
        "29,2%",
        "8,3%"
      ],
      [
        "13.",
        "",
        "Gesquiere, Amber",
        "10",
        "8",
        "Mittelblock",
        "Borken",
        "Belgien (BEL)",
        "27",
        "4",
        "3",
        "25,9%",
        "7,4%"
      ],
      [
        "16.",
        "",
        "Loker, Marika",
        "31",
        "10",
        "Diagonal",
        "Borken",
        "Deutschland (GER)",
        "90",
        "5",
        "6",
        "30,0%",
        "2,2%"
      ],
      [
        "18.",
        "",
        "Konjer, Chaine",
        "24",
        "9",
        "Zuspiel",
        "Borken",
        "Deutschland (GER)",
        "40",
        "4",
        "5",
        "27,5%",
        "0,0%"
      ],
      [
        "36.",
        "",
        "Rudde, Hannah",
        "27",
        "10",
        "Zuspiel",
        "Borken",
        "Deutschland (GER)",
        "60",
        "8",
        "5",
        "35,0%",
        "-6,7%"
      ]
    ]
  }
}
